{
  "name": "wastewater",
  "type": "source",
  "scripts": [
    {
      "path": "ingest.R",
      "manual": false,
      "frequency": 0,
      "last_run": "2026-01-31 04:08:54",
      "run_time": 3.367,
      "last_status": {
        "log": ["trying URL 'https://www.cdc.gov/wcms/vizdata/NCEZID_DIDRI/RSVStateLevelDownloadCSV.csv'", "downloaded 1.0 MB", "", "trying URL 'https://www.cdc.gov/wcms/vizdata/NCEZID_DIDRI/FluA/FluAStateMapDownloadCSV.csv'", "downloaded 1.1 MB", "", "trying URL 'https://www.cdc.gov/wcms/vizdata/NCEZID_DIDRI/SC2StateLevelDownloadCSV.csv'", "downloaded 1.6 MB", ""],
        "success": true
      }
    }
  ],
  "checked": "2025-10-15 02:35:00",
  "check_results": {
    "./data/wastewater/standard/data.csv.gz": []
  },
  "raw_state": {
    "raw/covid.csv.xz": "d4392435401555d9a0456cd78d473f38",
    "raw/flua.csv.xz": "faf815b5c2b3ac3c383630e3a9c50cf5",
    "raw/rsv.csv.xz": "2e9d3f44122d68b94ba356e576d014f3"
  },
  "standard_state": {
    "./data/wastewater/measure_info.json": "5d2fdee101826ff1f3493f4e01ff21bc",
    "./data/wastewater/standard/data.csv.gz": "b5b8dbbd693807dfe96ff0671fc661ac"
  }
}
