{
  "name": "wastewater",
  "type": "source",
  "scripts": [
    {
      "path": "ingest.R",
      "manual": false,
      "frequency": 0,
      "last_run": "2026-02-14 04:13:08",
      "run_time": 2.823,
      "last_status": {
        "log": ["trying URL 'https://www.cdc.gov/wcms/vizdata/NCEZID_DIDRI/RSVStateLevelDownloadCSV.csv'", "downloaded 1.1 MB", "", "trying URL 'https://www.cdc.gov/wcms/vizdata/NCEZID_DIDRI/FluA/FluAStateMapDownloadCSV.csv'", "downloaded 1.1 MB", "", "trying URL 'https://www.cdc.gov/wcms/vizdata/NCEZID_DIDRI/SC2StateLevelDownloadCSV.csv'", "downloaded 1.6 MB", ""],
        "success": true
      }
    }
  ],
  "checked": "2025-10-15 02:35:00",
  "check_results": {
    "./data/wastewater/standard/data.csv.gz": []
  },
  "raw_state": {
    "raw/covid.csv.xz": "ec026420e3c46390363f448dbab464db",
    "raw/flua.csv.xz": "adcc163b739b634d6228bed2dc66dfd6",
    "raw/rsv.csv.xz": "4924c9baea2f71e439f1ba158b4f9eef"
  },
  "standard_state": {
    "./data/wastewater/measure_info.json": "5d2fdee101826ff1f3493f4e01ff21bc",
    "./data/wastewater/standard/data.csv.gz": "b710a906b0e7e5f22633a5ec93577b9a"
  }
}
